X30TianChidiaoNaZhiTensorflow20Fix1/README.md
X30TianChidiaoNaZhiTensorflow20Fix1/__init__.py
X30TianChidiaoNaZhiTensorflow20Fix1/__main__.py
X30TianChidiaoNaZhiTensorflow20Fix1/file.epub
X30TianChidiaoNaZhiTensorflow20Fix1/index.html
X30TianChidiaoNaZhiTensorflow20Fix1/css/__init__.py
X30TianChidiaoNaZhiTensorflow20Fix1/css/annotations.css
X30TianChidiaoNaZhiTensorflow20Fix1/css/main.css
X30TianChidiaoNaZhiTensorflow20Fix1/css/normalize.css
X30TianChidiaoNaZhiTensorflow20Fix1/css/popup.css
X30TianChidiaoNaZhiTensorflow20Fix1/font/__init__.py
X30TianChidiaoNaZhiTensorflow20Fix1/font/fontello.eot
X30TianChidiaoNaZhiTensorflow20Fix1/font/fontello.svg
X30TianChidiaoNaZhiTensorflow20Fix1/font/fontello.ttf
X30TianChidiaoNaZhiTensorflow20Fix1/font/fontello.woff
X30TianChidiaoNaZhiTensorflow20Fix1/img/__init__.py
X30TianChidiaoNaZhiTensorflow20Fix1/img/annotator-glyph-sprite.png
X30TianChidiaoNaZhiTensorflow20Fix1/img/annotator-icon-sprite.png
X30TianChidiaoNaZhiTensorflow20Fix1/img/apple-touch-icon.png
X30TianChidiaoNaZhiTensorflow20Fix1/img/cancelfullscreen.png
X30TianChidiaoNaZhiTensorflow20Fix1/img/close.png
X30TianChidiaoNaZhiTensorflow20Fix1/img/fullscreen.png
X30TianChidiaoNaZhiTensorflow20Fix1/img/loader.gif
X30TianChidiaoNaZhiTensorflow20Fix1/img/menu-icon.png
X30TianChidiaoNaZhiTensorflow20Fix1/img/save.png
X30TianChidiaoNaZhiTensorflow20Fix1/img/saved.png
X30TianChidiaoNaZhiTensorflow20Fix1/img/settings-s.png
X30TianChidiaoNaZhiTensorflow20Fix1/img/settings.png
X30TianChidiaoNaZhiTensorflow20Fix1/img/star.png
X30TianChidiaoNaZhiTensorflow20Fix1/js/__init__.py
X30TianChidiaoNaZhiTensorflow20Fix1/js/epub.js
X30TianChidiaoNaZhiTensorflow20Fix1/js/epub.min.js
X30TianChidiaoNaZhiTensorflow20Fix1/js/epub.min.map
X30TianChidiaoNaZhiTensorflow20Fix1/js/hooks.min.js
X30TianChidiaoNaZhiTensorflow20Fix1/js/hooks.min.map
X30TianChidiaoNaZhiTensorflow20Fix1/js/reader.js
X30TianChidiaoNaZhiTensorflow20Fix1/js/reader.js.map
X30TianChidiaoNaZhiTensorflow20Fix1/js/reader.min.js
x30_tian_chidiao_na_zhi_tensorflow2_0_fix1-2025.3.24.1.dist-info/METADATA
x30_tian_chidiao_na_zhi_tensorflow2_0_fix1-2025.3.24.1.dist-info/WHEEL
x30_tian_chidiao_na_zhi_tensorflow2_0_fix1-2025.3.24.1.dist-info/entry_points.txt
x30_tian_chidiao_na_zhi_tensorflow2_0_fix1-2025.3.24.1.dist-info/top_level.txt
x30_tian_chidiao_na_zhi_tensorflow2_0_fix1-2025.3.24.1.dist-info/RECORD
